sndpythons/__init__.py
sndpythons-0.1.0.dist-info/METADATA
sndpythons-0.1.0.dist-info/WHEEL
sndpythons-0.1.0.dist-info/RECORD
